{
  "index": "19",
  "name": "Forgotten Crypt",
  "edition": "gh",
  "unlocks": [
    "27"
  ],
  "requires": [
    [
      "14"
    ]
  ],
  "monsters": [
    "cultist",
    "living-bones",
    "living-corpse",
    "living-spirit"
  ],
  "objectives": [
    {
      "name": "Hail",
      "escort": true,
      "health": "4+(2xL)",
      "marker": "a",
      "actions": [
        {
          "type": "move",
          "value": 2,
          "subActions": [
            {
              "type": "custom",
              "value": "%data.scenario.rules.gh.19.1%",
              "small": true
            }
          ]
        }
      ]
    }
  ],
  "rules": [
    {
      "round": "R == 1",
      "start": true,
      "figures": [
        {
          "identifier": {
            "type": "character",
            "name": ".*"
          },
          "type": "amAdd",
          "value": "curse:3",
          "scenarioEffect": true
        }
      ]
    },
    {
      "round": "true",
      "once": true,
      "spawns": [
        {
          "monster": {
            "name": "cultist",
            "player2": "normal"
          },
          "marker": "c"
        },
        {
          "count": 2,
          "monster": {
            "name": "cultist",
            "player3": "normal",
            "player4": "normal"
          },
          "marker": "c"
        }
      ],
      "requiredRooms": [
        3
      ]
    },
    {
      "round": "true",
      "once": true,
      "spawns": [
        {
          "monster": {
            "name": "living-spirit",
            "player2": "normal",
            "player3": "normal"
          },
          "marker": "d"
        },
        {
          "count": 2,
          "monster": {
            "name": "living-spirit",
            "player4": "normal"
          },
          "marker": "d"
        }
      ],
      "requiredRooms": [
        4
      ]
    },
    {
      "round": "true",
      "once": true,
      "spawns": [
        {
          "monster": {
            "name": "living-bones",
            "player2": "normal"
          },
          "marker": "e"
        },
        {
          "count": 2,
          "monster": {
            "name": "living-bones",
            "player3": "normal",
            "player4": "normal"
          },
          "marker": "e"
        }
      ],
      "requiredRooms": [
        5
      ]
    }
  ],
  "rooms": [
    {
      "roomNumber": 1,
      "ref": "d2a",
      "initial": true,
      "rooms": [
        2
      ],
      "monster": [
        {
          "name": "cultist",
          "type": "normal"
        },
        {
          "name": "cultist",
          "type": "normal"
        },
        {
          "name": "living-bones",
          "player3": "normal",
          "player4": "elite"
        }
      ],
      "objectives": [
        1
      ]
    },
    {
      "roomNumber": 2,
      "ref": "d1a",
      "rooms": [
        3
      ],
      "monster": [
        {
          "name": "living-bones",
          "type": "normal"
        },
        {
          "name": "living-bones",
          "player3": "normal",
          "player4": "normal"
        },
        {
          "name": "living-spirit",
          "type": "normal"
        },
        {
          "name": "living-spirit",
          "type": "normal"
        },
        {
          "name": "living-spirit",
          "player4": "elite"
        }
      ]
    },
    {
      "roomNumber": 3,
      "ref": "c2b",
      "marker": "1",
      "rooms": [
        4
      ],
      "monster": [
        {
          "name": "cultist",
          "type": "elite"
        },
        {
          "name": "living-bones",
          "type": "normal"
        },
        {
          "name": "living-bones",
          "player3": "normal",
          "player4": "normal"
        },
        {
          "name": "living-bones",
          "player3": "normal",
          "player4": "normal"
        },
        {
          "name": "living-bones",
          "player4": "normal"
        }
      ]
    },
    {
      "roomNumber": 4,
      "ref": "c1a",
      "marker": "2",
      "rooms": [
        5
      ],
      "monster": [
        {
          "name": "living-corpse",
          "type": "elite"
        },
        {
          "name": "living-corpse",
          "player3": "normal",
          "player4": "normal"
        },
        {
          "name": "living-corpse",
          "player4": "normal"
        }
      ]
    },
    {
      "roomNumber": 5,
      "ref": "i1b",
      "marker": "3",
      "treasures": [
        17
      ],
      "monster": [
        {
          "name": "cultist",
          "player2": "normal",
          "player3": "normal",
          "player4": "elite"
        },
        {
          "name": "cultist",
          "player2": "normal",
          "player3": "normal",
          "player4": "elite"
        },
        {
          "name": "living-corpse",
          "type": "normal"
        },
        {
          "name": "living-corpse",
          "type": "normal"
        },
        {
          "name": "living-corpse",
          "player3": "elite",
          "player4": "elite"
        }
      ]
    }
  ]
}