{
  "index": "51",
  "name": "The Void",
  "edition": "gh",
  "monsters": [
    "the-gloom"
  ],
  "rules": [
    {
      "round": "R == 1",
      "start": true,
      "figures": [
        {
          "identifier": {
            "type": "character",
            "name": ".*"
          },
          "type": "amAdd",
          "value": "curse:3",
          "scenarioEffect": true
        }
      ]
    }
  ],
  "rooms": [
    {
      "roomNumber": 1,
      "ref": "d1a",
      "initial": true,
      "treasures": [
        56
      ],
      "monster": [
        {
          "name": "the-gloom",
          "type": "normal"
        }
      ]
    }
  ]
}